essencia_engine/__init__.py
essencia_engine/base/__init__.py
essencia_engine/base/context.py
essencia_engine/base/data.py
essencia_engine/base/database.py
essencia_engine/base/endpoint.py
essencia_engine/base/enums.py
essencia_engine/base/function.py
essencia_engine/base/jj.py
essencia_engine/base/middleware.py
essencia_engine/base/model.py
essencia_engine/base/ntuple.py
essencia_engine/base/security.py
essencia_engine/base/session.py
essencia_engine/base/setup.py
essencia_engine/base/types.py
essencia_engine/endpoints.py
essencia_engine/models.py
essencia_engine/views.py
essencia_engine-0.1.0.dist-info/WHEEL
essencia_engine-0.1.0.dist-info/METADATA
essencia_engine-0.1.0.dist-info/RECORD
